portolan/__init__.py
portolan/data.py
portolan/portolan.py
portolan-1.0.1.dist-info/DESCRIPTION.rst
portolan-1.0.1.dist-info/METADATA
portolan-1.0.1.dist-info/RECORD
portolan-1.0.1.dist-info/WHEEL
portolan-1.0.1.dist-info/metadata.json
portolan-1.0.1.dist-info/top_level.txt
