Metadata-Version: 2.0
Name: portolan
Version: 1.0.1
Summary: Convert between compass points and degrees
Home-page: https://github.com/fitnr/portolan
Author: Neil Freeman
Author-email: contact@fakeisthenewreal.org
License: GPL
Platform: UNKNOWN
Classifier: License :: OSI Approved :: GNU General Public License v3 (GPLv3)
Classifier: Programming Language :: Python :: 2
Classifier: Programming Language :: Python :: 2.7
Classifier: Programming Language :: Python :: 3.3
Classifier: Programming Language :: Python :: 3.4
Classifier: Topic :: Scientific/Engineering :: Atmospheric Science
Classifier: Intended Audience :: Science/Research
